{
    "translation": {
        "description": {
            "short_name": "ar",
            "id": 4,
            "part1": "موضوع هذه النشرة ستساعدك هذه النشرة على فهم كيفية تكوين الفقرات ، وكيفية تطوير فقرات أقوى ، وكيفية التعبير عن أفكارك بشكل كامل وواضح. ما هي الفقرة؟ الفقرات هي اللبنات الأساسية للأوراق. يعرّف العديد من الطلاب الفقرات من حيث الطول: الفقرة هي مجموعة من خمس جمل على الأقل ، والفقرة بطول نصف صفحة ، إلخ. يتم تعريف الفقرة على أنها مجموعة من الجمل أو جملة واحدة تشكل وحدة' (Lunsford and Connors 116). لا يحدد الطول والمظهر ما إذا كان المقطع في الورقة فقرة أم لا. على سبيل المثال ، في بعض أنماط الكتابة ، وخاصة الأنماط الصحفية ، يمكن أن تكون الفقرة بطول جملة واحدة فقط. في النهاية ، الفقرة هي جملة أو مجموعة من الجمل التي تدعم فكرة رئيسية واحدة. في هذه النشرة ، سوف نشير إلى هذا باسم 'الفكرة المسيطرة'، لأنها تتحكم في ما يحدث في بقية الفقرة. كيف أقرر ما أضعه في فقرة؟ قبل أن تتمكن من البدء في تحديد تكوين فقرة معينة ، يجب عليك أولاً تحديد الحجة وبيان أطروحة العمل لورقتك البحثية. ما هي أهم فكرة تحاول نقلها للقارئ؟ يجب أن تكون المعلومات الواردة في كل فقرة مرتبطة بهذه الفكرة. بمعنى آخر ، يجب أن تذكر فقراتك القارئ بوجود علاقة متكررة بين أطروحتك والمعلومات الواردة في كل فقرة. تعمل أطروحة العمل كبذرة تنمو منها ورقتك وأفكارك. العملية برمتها هي عملية عضوية - تطور طبيعي من بذرة إلى ورقة كاملة حيث توجد علاقات عائلية مباشرة بين جميع الأفكار الواردة في الورقة. يبدأ القرار بشأن ما يجب وضعه في فقراتك بإنبات بذرة من الأفكار ؛ تُعرف 'عملية الإنبا' هذه باسم العصف الذهني. هناك العديد من تقنيات العصف الذهني. أيًا كانت المرحلة التي تختارها ، لا يمكن تخطي هذه المرحلة من تطوير الفقرة. يمكن أن يكون بناء الفقرات بمثابة بناء ناطحة سحاب: يجب أن يكون هناك أساس جيد التخطيط يدعم ما تقوم ببنائه. يمكن أن تتسبب أي شقوق أو تناقضات أو فساد آخر في الأساس في انهيار الورق بالكامل",
            "part2": "تعلم React",
            "Nav": "التدويل في React",
            "head": "مرحبًا بك في React",
            "url": "حول",
            "home": "الصفحة الرئيسية",
            "subHome": "هذه هي الصفحة الرئيسية",
            "subAbout": "هذا عن الصفحة"
        },
        "login": {
            "leftSide": {
                "tabs": {
                    "aboutus": {
                        "name": "معلومات عنا",
                        "title": "ضمان جودة التعليم (EQA) إطار اعتماد لـ NCAAA & ABET",
                        "subTitle": "EQA هو تطبيق قائم على الويب للأتمتة",
                        "description": "EQA هو تطبيق قائم على الويب لأتمتة أنشطة الاعتماد الأكاديمي من البداية إلى النهاية والتنفيذ الصارم لمتطلبات الامتثال المحددة من قبل وكالات الاعتماد في جميع أنحاء العالم لتحسين أساليب وممارسات تقديم التعليم.",
                        "learnMoreBtn": "يتعلم أكثر",
                        "findUs": "تجدنا على وسائل التواصل الاجتماعي"
                    },
                    "noticeboard": {
                        "name": "لوح الإعلانات",
                        "title": "الإعلانات",
                        "subTitle": ".هذه هي الإخطارات الأخيرة المدرجة أدناه"
                    }
                }
            },
            "rightSide":{
                "loginContainer":{
                    "img":{
                        "title":"جامعة EQA",
                        "alt":"جامعة EQA"
                    },
                    "title":"تسجيل الدخول بحسابك",
                    "formInputs":{
                        "userName":{
                            "label":"اسم االمستخدم",
                            "placeHolder":"ادخل اسم المستخدم"
                        },
                        "password":{
                            "label":"كلمة المرور",
                            "placeHolder":"أدخل كلمة المرور"
                        },
                        "rememberMeText":"تذكرني لمدة 30 يومًا القادمة",
                        "btnLogin":"تسجيل الدخول",
                        "forgetPassword":"هل نسيت كلمة السر؟",
                        "clickHere":"انقر هنا"
                    }
                }
            }
        },
        "forgetPassword": {
            "title": "هل نسيت كلمة السر؟",
            "subTitle":"يمكنك إعادة تعيين كلمة المرور الخاصة بك هنا.",
            "img":{
                "img1":{
                    "title":"جامعة EQA",
                    "alt":"جامعة EQA"
                },
                "img2":{
                    "title":"نسيت كلمة المرور يمكنك إعادة تعيين هنا لا تقلق",
                    "alt":"نسيت كلمة المرور يمكنك إعادة تعيين هنا لا تقلق"
                }
            },
            "formInputs": {
                "userName": {
                    "label": "عنوان البريد الإلكتروني",
                    "placeHolder": "example@gmail.com"
                },
                "btnResetPassword": "إعادة تعيين كلمة المرور"
            }
        }
    }
}